thaiqrpayment/__init__.py
thaiqrpayment/assets/logo.png
thaiqrpayment/assets/template.png
thaiqrpayment-0.1.0.dist-info/LICENSE
thaiqrpayment-0.1.0.dist-info/METADATA
thaiqrpayment-0.1.0.dist-info/WHEEL
thaiqrpayment-0.1.0.dist-info/top_level.txt
thaiqrpayment-0.1.0.dist-info/RECORD
