Metadata-Version: 2.1
Name: thaiqrpayment
Version: 0.1.0
Summary: Thai QR Payment Generator
Home-page: https://github.com/kittinan/thai-qr-payment
Author: Kittinan Srithaworn
License: MIT
Project-URL: Bug Reports, https://github.com/kittinan/thai-qr-payment/issues
Project-URL: Source, https://github.com/kittinan/thai-qr-payment
Keywords: Thai QR Payment Generator
Platform: UNKNOWN
Classifier: Programming Language :: Python :: 3
Classifier: License :: OSI Approved :: MIT License
Classifier: Operating System :: OS Independent
Requires-Python: >=3.6
Requires-Dist: qrcode
Requires-Dist: pillow
